odoo/addons/sm_rest_api/__init__.py
odoo/addons/sm_rest_api/__manifest__.py
odoo/addons/sm_rest_api/models/__init__.py
odoo/addons/sm_rest_api/models/models.py
odoo11_addon_sm_rest_api-11.0.0.0.2.dist-info/METADATA
odoo11_addon_sm_rest_api-11.0.0.0.2.dist-info/WHEEL
odoo11_addon_sm_rest_api-11.0.0.0.2.dist-info/top_level.txt
odoo11_addon_sm_rest_api-11.0.0.0.2.dist-info/RECORD
