Metadata-Version: 2.1
Name: odoo11-addon-sm-rest-api
Version: 11.0.0.0.2
Summary: REST API implementation for carsharing system
Home-page: http://www.yourcompany.com
Author: Som Mobilitat
License: UNKNOWN
Platform: UNKNOWN
Classifier: Programming Language :: Python
Classifier: Framework :: Odoo
Requires-Python: >=2.7, !=3.0.*, !=3.1.*, !=3.2.*, !=3.3.*, !=3.4.*
Requires-Dist: odoo (<11.1dev,>=11.0a)
